django_cleanup_ignore_directories/__init__.py
django_cleanup_ignore_directories/apps.py
django_cleanup_ignore_directories/cache.py
django_cleanup_ignore_directories/cleanup.py
django_cleanup_ignore_directories/handlers.py
django_cleanup_ignore_directories/signals.py
django_cleanup_ignore_directories-1.0.1.dist-info/LICENSE
django_cleanup_ignore_directories-1.0.1.dist-info/METADATA
django_cleanup_ignore_directories-1.0.1.dist-info/WHEEL
django_cleanup_ignore_directories-1.0.1.dist-info/top_level.txt
django_cleanup_ignore_directories-1.0.1.dist-info/RECORD
