Metadata-Version: 2.1
Name: django-cleanup-ignore-directories
Version: 1.0.1
Summary: Extension of the django-cleanup project v4.0.0. Allows ignoring specified user directories
Home-page: https://github.com/MausamGaurav/django_cleanup_ignore_directories
License: UNKNOWN
Platform: UNKNOWN
Classifier: Programming Language :: Python :: 3
Classifier: Framework :: Django :: 2.2
Classifier: License :: OSI Approved :: MIT License
Classifier: Operating System :: OS Independent
Requires-Python: >=3.6
